g/__init__.py
g/g.py
g/gitoptions.py
g/helper.py
g/shared.py
git/__init__.py
git/gitoptions.py
git/helper.py
git/main.py
git/shared.py
git/shell_complete.py
pyzgit-1.3.dist-info/LICENSE
pyzgit-1.3.dist-info/METADATA
pyzgit-1.3.dist-info/WHEEL
pyzgit-1.3.dist-info/entry_points.txt
pyzgit-1.3.dist-info/top_level.txt
pyzgit-1.3.dist-info/RECORD
