Metadata-Version: 2.1
Name: pyzgit
Version: 1.3
Summary: Simple terminal tool of Git.
Home-page: https://github.com/zlj-zz/pyzgit.git
Author: Zachary Zhang
Author-email: zlj1997122@outlook.com
License: UNKNOWN
Platform: UNKNOWN
Classifier: Programming Language :: Python :: 3.5
Classifier: Programming Language :: Python :: 3.6
Classifier: Programming Language :: Python :: 3.7
Classifier: Programming Language :: Python :: 3.8
Classifier: Programming Language :: Python :: 3.9
Classifier: Intended Audience :: Developers
Classifier: License :: OSI Approved :: MIT License
Classifier: Operating System :: OS Independent
Requires-Python: >=3.5
